[
    {
        "id": "6807be7780183",
        "title": "Is Make In India Failing? | Case study",
        "link": "https:\/\/youtu.be\/0DrAzdRo3RM?feature=shared",
        "added_at": "2025-04-22 16:06:15"
    },
    {
        "id": "6807c1e1d56e8",
        "title": "Harsha Bhogle - Fear of Failure",
        "link": "https:\/\/youtu.be\/drKNx8U49WQ?feature=shared",
        "added_at": "2025-04-22 16:20:49"
    },
    {
        "id": "6807c236701fd",
        "title": "West Bengal WAQF Protests ,Murshidabad | 2025 Viral Video | Latest Telugu Facts | VR Raja Facts",
        "link": "https:\/\/youtu.be\/yg06yKbkglE?feature=shared",
        "added_at": "2025-04-22 16:22:14"
    },
    {
        "id": "6807c2a631eeb",
        "title": "WAQF Bill Explained in Telugu \u2696\ufe0f\u2757#ismartshivafacts #waqfbill",
        "link": "https:\/\/youtu.be\/BzY3wPC-oKE?feature=shared",
        "added_at": "2025-04-22 16:24:06"
    },
    {
        "id": "6807c2e1a8253",
        "title": "Is Digital India a Failure? Are there Gaps in UPI, ONDC and OCEN? Detailed Analysis",
        "link": "https:\/\/youtu.be\/TnEyFSToGbg?feature=shared",
        "added_at": "2025-04-22 16:25:05"
    },
    {
        "id": "6807c2f735c84",
        "title": "How to Improve Your Critical Thinking Skills",
        "link": "https:\/\/youtu.be\/JOFrjc6u47U?feature=shared",
        "added_at": "2025-04-22 16:25:27"
    },
    {
        "id": "6807c30cc57f9",
        "title": "Think Fast, Talk Smart: Communication Techniques",
        "link": "https:\/\/youtu.be\/HAnw168huqA?feature=shared",
        "added_at": "2025-04-22 16:25:48"
    },
    {
        "id": "6807d0eb50fdc",
        "title": "MODI\u2019s MASTERSTROKE Budget 2025 Analysed in Simple words: Budget 2025 case study",
        "link": "https:\/\/youtu.be\/qBOFexfWS4k?feature=shared",
        "added_at": "2025-04-22 17:24:59"
    },
    {
        "id": "68086f0b49117",
        "title": "What's An Election in Kashmir Achieved? End Result is Terror Infiltration | Arnab's View",
        "link": "https:\/\/youtu.be\/f9AVTEXC09Q?feature=shared",
        "added_at": "2025-04-23 04:39:39"
    },
    {
        "id": "680b4f71353f8",
        "title": "India Pakistan W@r Situation, Kashmir Pahalgam Incident Explained By VR Raja | Latest Facts",
        "link": "https:\/\/youtu.be\/PFeIjYf6mfk?feature=shared",
        "added_at": "2025-04-25 09:01:37"
    },
    {
        "id": "680b4f7b97ced",
        "title": "India Strong Warning to Pakistan Because of Kashmir Pahalgam Incident | Latest Facts | VR Raja Facts",
        "link": "https:\/\/youtu.be\/Fm5KSInSxLU?feature=shared",
        "added_at": "2025-04-25 09:01:47"
    },
    {
        "id": "6814aaa706b06",
        "title": "ETTABOYINA SAI SHIVANI - UPSC 2024, AIR - 11 | UPSC Topper Mock Interview | PW OnlyIAS IGP Program",
        "link": "https:\/\/youtu.be\/HvZ-APasHmE?si=IxuA7921USsnH8Bm",
        "added_at": "2025-05-02 11:21:11"
    },
    {
        "id": "68176e32c5bab",
        "title": "Masterstroke or Death of Democracy: One Nation One Election EXPLAINED",
        "link": "https:\/\/youtu.be\/nNbphew2mpU?si=n_qw9crcjcEP5ulR",
        "added_at": "2025-05-04 13:40:02"
    },
    {
        "id": "6820ee375a9cf",
        "title": "Dark Reality Of UPSC Exams | Case Study | Kranthi Vlogger",
        "link": "https:\/\/youtu.be\/yibJhI_gGBw?si=oQsHY_WoX_ZpahrH",
        "added_at": "2025-05-11 18:36:39"
    }
]